pyerm/__init__.py
pyerm/database/__init__.py
pyerm/database/dbbase.py
pyerm/database/experiment.py
pyerm/database/tables.py
pyerm/database/utils.py
pyerm/scripts/__init__.py
pyerm/scripts/db_merge.py
pyerm/scripts/erm_webui.py
pyerm/scripts/export_data.py
pyerm/scripts/initialize.py
pyerm/webUI/__init__.py
pyerm/webUI/analysis.py
pyerm/webUI/app.py
pyerm/webUI/details.py
pyerm/webUI/home.py
pyerm/webUI/record.py
pyerm/webUI/tables.py
pyerm/webUI/utils.py
pyerm/webUI/language_data/string_Chinese.xml
pyerm/webUI/language_data/string_English.xml
pyerm-0.3.8.dist-info/METADATA
pyerm-0.3.8.dist-info/WHEEL
pyerm-0.3.8.dist-info/entry_points.txt
pyerm-0.3.8.dist-info/top_level.txt
pyerm-0.3.8.dist-info/RECORD
