Metadata-Version: 2.4
Name: pyerm
Version: 0.3.8
Summary: This project is an local experiment record manager for python based on SQLite DMS, suitable for recording experiment and analysing experiment data with a web UI, which can help you efficiently save your experiment settings and results for later analysis.
Home-page: https://github.com/Mr-SGXXX/pyerm
Author: Yuxuan Shao
Author-email: yx_shao@qq.com
License: MIT
Classifier: Programming Language :: Python :: 3
Classifier: License :: OSI Approved :: MIT License
Classifier: Operating System :: OS Independent
Requires-Python: >=3.9
Requires-Dist: pandas
Requires-Dist: pillow
Requires-Dist: xlsxwriter
Requires-Dist: numpy
Requires-Dist: matplotlib
Requires-Dist: seaborn
Requires-Dist: streamlit>=1.39.0
Dynamic: author
Dynamic: author-email
Dynamic: classifier
Dynamic: description
Dynamic: description-content-type
Dynamic: home-page
Dynamic: license
Dynamic: requires-dist
Dynamic: requires-python
Dynamic: summary
